{
	"QuizQuestions":[
		{
			"q_en":"Which among the following period of the stone age first witnessed the domestication of animals?",
            "a_en":"Paleolithic Age",
            "b_en":"Chalcolithic Age",
            "c_en":"Neolithic Age",
            "d_en":"Mesolithic Age",
            "e_en":"None of the above / More than one of the above",
            "q_hin":"पाषाण युग के निम्नलिखित में से किस काल में सबसे पहले जानवरों को पालतू बनाया गया था?",
            "a_hin":"पुरापाषाण युग",
            "b_hin":"ताम्र पाषाण युग",
            "c_hin":"नवपाषाण युग",
            "d_hin":"मध्यपाषाण युग",
            "e_hin":"उपरोक्त में से कोई नहीं/उपर्युक्त में से एक से अधिक।",
            "ans":"d"
		},       
		{
			"q_en":"Which one of the following ancient towns is well known for its elaborate system of water harvesting and management by building a series of dams and channelizing water into connected reservoirs?",
            "a_en":"Dholavira",
            "b_en":"Kalibangan",
            "c_en":"Rakhigarhi",
            "d_en":"Ropar",
            "e_en":"None of the above / More than one of the above",
            "q_hin":"निम्नलिखित प्राचीन नगरों में से कौन-सा एक बांधों की श्रृंखला बनाकर और जुड़े जलाशयों में जल को प्रवाहित करके जल संचयन और प्रबंधन की विस्तृत प्रणाली के लिए प्रसिद्ध है?",
            "a_hin":"धौलावीरा",
            "b_hin":"कालीबंगा",
            "c_hin":"राखीगढ़ी",
            "d_hin":"रोपड़",
            "e_hin":"उपरोक्त में से कोई नहीं/उपर्युक्त में से एक से अधिक।",
            "ans":"a"
		},       
		{
			"q_en":"Who among the following rulers transferred his capital from Rajgir to Patliputra?",
            "a_en":"Ajatastaru",
            "b_en":"Udayin",
            "c_en":"Ashoka",
            "d_en":"Vishnugupta",
            "e_en":"None of the above / More than one of the above",
            "q_hin":"इनमें से किस शासन ने अपनी राजधानी को राजगीर से पाटलिपुत्र स्थानांतरित किया था?",
            "a_hin":"अजातशत्रु",
            "b_hin":"उदयिन",
            "c_hin":"अशोक",
            "d_hin":"विष्णुगुप्त",
            "e_hin":"उपरोक्त में से कोई नहीं/उपर्युक्त में से एक से अधिक।",
            "ans":"b"
        },       
        {
            "q_en":"The great Mauryan Emperor Ashoka patronized which sect of Buddhism?",
            "a_en":"Mahayana",
            "b_en":"Hinayana",
            "c_en":"Vajrayana",
            "d_en":"Tantric Buddhism",
            "e_en":"None of the above / More than one of the above",
            "q_hin":"महान मौर्य सम्राट अशोक ने बौद्ध धर्म के किस संप्रदाय को संरक्षण प्रदान किया था?",
            "a_hin":"महायान",
            "b_hin":"हीनयान",
            "c_hin":"वज्रयान",
            "d_hin":"तांत्रिक बौद्ध धर्म",
            "e_hin":"उपरोक्त में से कोई नहीं/उपर्युक्त में से एक से अधिक।",
            "ans":"b"
        },       
        {
            "q_en":"The earliest Buddhist literature which deals with the stories of the various birth of Buddha is",
            "a_en":"Vinaya pitakas",
            "b_en":"Sutta pitakas",
            "c_en":"Abhidamma pitakas",
            "d_en":"Jatakas",
            "e_en":"None of the above / More than one of the above",
            "q_hin":"प्राचीनतम बौद्ध साहित्य जो बुद्ध के विभिन्न जन्मों की कहानियों से संबंधित है, वे हैं:",
            "a_hin":"विनय पिटक",
            "b_hin":"सुत्तपिटक",
            "c_hin":"अभिधम्म पिटक",
            "d_hin":"जातक",
            "e_hin":"उपरोक्त में से कोई नहीं/उपर्युक्त में से एक से अधिक।",
            "ans":"d"
        },       
        {
            "q_en":"Where was the second Jain council held?",
            "a_en":"Pataliputra",
            "b_en":"Vallabhi",
            "c_en":"Vaishali",
            "d_en":"Rajgir",
            "e_en":"None of the above / More than one of the above",
            "q_hin":"दूसरी जैन संगीति कहाँ आयोजित की गई थी?",
            "a_hin":"पाटलिपुत्र",
            "b_hin":"वल्लभी",
            "c_hin":"वैशाली",
            "d_hin":"राजगीर",
            "e_hin":"उपरोक्त में से कोई नहीं/उपर्युक्त में से एक से अधिक।",
            "ans":"b"
        },       
        {
            "q_en":"Who among the following Sunga ruler destroyed the Sanchi Stupa?",
            "a_en":"Pushyamitra Shunga",
            "b_en":"Mitra Shunga",
            "c_en":"Harsh Shunga",
            "d_en":"Rana Pratap Shunga",
            "e_en":"None of the above / More than one of the above",
            "q_hin":"निम्नलिखित में से किस शुंग शासक ने सांची के स्तूप को नष्ट किया था?",
            "a_hin":"पुष्यमित्र शुंग",
            "b_hin":"मित्र शुंग",
            "c_hin":"हर्ष शुंग",
            "d_hin":"राणा प्रताप शुंग",
            "e_hin":"उपरोक्त में से कोई नहीं/उपर्युक्त में से एक से अधिक।",
            "ans":"a"
        },       
        {
            "q_en":"With reference to the period of the Gupta kingdom in ancient India, which of the following terms refer to kinds of taxes?",
            "a_en":"Bhaga",
            "b_en":"Hiranya",
            "c_en":"Udianga",
            "d_en":"Jatakas",
            "e_en":"None of the above / More than one of the above",
            "q_hin":"प्राचीन भारत में गुप्त साम्राज्य की अवधि के संदर्भ में, निम्नलिखित में से कौन सा शब्द करों के प्रकारों को दर्शाता है?",
            "a_hin":"भाग",
            "b_hin":"हिरण्य",
            "c_hin":"उदियांग",
            "d_hin":"जातक",
            "e_hin":"उपरोक्त में से कोई नहीं/उपर्युक्त में से एक से अधिक।",
            "ans":"e"
        },
        {
            "q_en":"Who wrote the great literary work 'Mricchakatika'?",
            "a_en":"Kalidasa",
            "b_en":"Shudraka",
            "c_en":"Harsha",
            "d_en":"Bhaasa",
            "e_en":"None of the above / More than one of the above",
            "q_hin":"महान साहित्यिक कृति 'मृच्छकटिकम्' किसके द्वारा लिखी गयी थी?",
            "a_hin":"कालिदास",
            "b_hin":"शूद्रक",
            "c_hin":"हर्ष",
            "d_hin":"भासा",
            "e_hin":"उपरोक्त में से कोई नहीं/उपर्युक्त में से एक से अधिक।",
            "ans":"b"
        },
        {
            "q_en":"The Greek ambassador Deimachus visited the court of which of the following rulers?",
            "a_en":"Ashoka",
            "b_en":"Samudragupta",
            "c_en":"Chandra Gupta Maurya",
            "d_en":"Bindusara",
            "e_en":"None of the above / More than one of the above",
            "q_hin":"निम्नलिखित में से किस शासक के दरबार में यूनानी राजदूत डाईमेकस आया था?",
            "a_hin":"अशोक",
            "b_hin":"समुद्रगुप्त",
            "c_hin":"चंद्रगुप्त मौर्य",
            "d_hin":"बिन्दुसार",
            "e_hin":"उपरोक्त में से कोई नहीं/उपर्युक्त में से एक से अधिक।",
            "ans":"d"
        }
	]
}