{
	"QuizQuestions":[
		{
			"q_en":"Which among the following is not one of the contributions made by the moderate nationalist?",
            "a_en":"Economic critique of British imperialism.",
            "b_en":"Laid emphasis on self reliance.",
            "c_en":"They gave the slogan 'No taxation without representation.'",
            "d_en":"Defence of civil rights was made an integral part of the freedom struggle.",
            "e_en":"None of the above/More than one of the above",
            "q_hin":"निम्न में से कौन उदारवादी राष्ट्रवादी द्वारा दिए गए योगदानों में से एक नहीं है?",
            "a_hin":"ब्रिटिश साम्राज्यवाद की आर्थिक आलोचना।",
            "b_hin":"स्वावलंबन पर जोर दिया।",
            "c_hin":"उन्होंने 'प्रतिनिधित्व के बिना कोई कराधान नहीं' का नारा दिया।",
            "d_hin":"नागरिक अधिकारों की रक्षा को स्वतंत्रता संग्राम का एक अभिन्न अंग बनाया गया था।",
            "e_hin":"उपरोक्त में से कोई नहीं/उपरोक्त में से एक से अधिक",
            "ans":"b"
		},       
		{
			"q_en":"With reference to the annulment of Partition of Bengal in 1911, Which of the statements given is/are correct?",
            "a_en":"It was done by Viceroy Lord Minto-II.",
            "b_en":"It was done in order to curb the menace of revolutionary nationalists.",
            "c_en":"It was welcomed by the Muslim political elite.",
            "d_en":"It was welcomed by Congress Party.",
            "e_en":"None of the above/More than one of the above",
            "q_hin":"1911 में बंगाल विभाजन की समाप्ति के संदर्भ में, दिए गए कथनों में से कौन-सा/से सही है/हैं?",
            "a_hin":"यह वाइसराय लॉर्ड मिंटो-द्वितीय द्वारा किया गया था।",
            "b_hin":"यह क्रांतिकारी राष्ट्रवादियों के खतरे को रोकने के लिए किया गया था।",
            "c_hin":"मुस्लिम राजनीतिक अभिजात वर्ग ने इसका स्वागत किया।",
            "d_hin":"इसका कांग्रेस पार्टी ने स्वागत किया",
            "e_hin":"उपरोक्त में से कोई नहीं/उपरोक्त में से एक से अधिक",
            "ans":"b"
		},       
		{
			"q_en":"Who among the following had organised a secret society of revolutionaries named Abhinav Bharat in 1904?",
            "a_en":"Khudiram Bose",
            "b_en":"Shyamji Krishna Verma",
            "c_en":"Har Dayal",
            "d_en":"V D Savarkar",
            "e_en":"None of the above/More than one of the above",
            "q_hin":"निम्नलिखित में से किसने 1904 में अभिनव भारत नामक क्रांतिकारियों का एक गुप्त समाज आयोजित किया था?",
            "a_hin":"खुदीराम बोस",
            "b_hin":"श्याम जी कृष्ण वर्मा",
            "c_hin":"हर दयाल",
            "d_hin":"वी डी सावरकर",
            "e_hin":"उपरोक्त में से कोई नहीं/उपरोक्त में से एक से अधिक",
            "ans":"d"
        },       
        {
            "q_en":"The Lucknow Pact of 1916 was made between-",
            "a_en":"Indian National Congress and All India Muslim League",
            "b_en":"The moderates and the extremists",
            "c_en":"British Government and All India Muslim League",
            "d_en":"Indian National Congress and British Government",
            "e_en":"None of the above/More than one of the above",
            "q_hin":"1916 का लखनऊ समझौता ______ के बीच हुआ था।",
            "a_hin":"भारतीय राष्ट्रीय कांग्रेस और अखिल भारतीय मुस्लिम लीग",
            "b_hin":"नरम दल और गरम दल",
            "c_hin":"ब्रिटिश सरकार और अखिल भारतीय मुस्लिम लीग",
            "d_hin":"भारतीय राष्ट्रीय कांग्रेस और ब्रिटिश सरकार",
            "e_hin":"उपरोक्त में से कोई नहीं/उपरोक्त में से एक से अधिक",
            "ans":"a"
        },       
        {
            "q_en":"Who described Jinnah as 'the ambassador of Hindu-Muslim Unity'?",
            "a_en":"Mahatma Gandhi",
            "b_en":"Sarojini Naidu",
            "c_en":"Jawaharlal Nehru",
            "d_en":"Tej Bahadur Sapru",
            "e_en":"None of the above/More than one of the above",
            "q_hin":"जिन्ना को किसने 'हिंदू-मुस्लिम एकता का राजदूत' बताया?",
            "a_hin":"महात्मा गांधी",
            "b_hin":"सरोजिनी नायडू",
            "c_hin":"जवाहर लाल नेहरू",
            "d_hin":"तेज बहादुर सप्रू",
            "e_hin":"उपरोक्त में से कोई नहीं/उपरोक्त में से एक से अधिक",
            "ans":"b"
        },       
        {
            "q_en":"Which among the following Acts of British India, provided for the payment of Secretary of State for India out of the British exchequer and not out of India exchequer?",
            "a_en":"Government of India Act, 1935",
            "b_en":"Government of India Act, 1919",
            "c_en":"Government of India Act, 1909",
            "d_en":"Government of India Act, 1858",
            "e_en":"None of the above/More than one of the above",
            "q_hin":"ब्रिटिश भारत के निम्नलिखित में से किस अधिनियम में भारत के लिए राज्य सचिव के भुगतान का प्रावधान ब्रिटिश राजकोष से किया गया था न कि भारत के राजकोष से?",
            "a_hin":"भारत सरकार अधिनियम, 1935",
            "b_hin":"भारत सरकार अधिनियम, 1919",
            "c_hin":"भारत सरकार अधिनियम, 1909",
            "d_hin":"भारत सरकार अधिनियम, 1858",
            "e_hin":"उपरोक्त में से कोई नहीं/उपरोक्त में से एक से अधिक",
            "ans":"b"
        },       
        {
            "q_en":"Who among the following was elected as the President All India Khilafat Conference met at Delhi in 1919?",
            "a_en":"Motilal Nehru",
            "b_en":"Mahatma Gandhi",
            "c_en":"M Ali Jinnah",
            "d_en":"Shaukat Ali",
            "e_en":"None of the above/More than one of the above",
            "q_hin":"1919 में दिल्ली में हुए अखिल भारतीय खिलाफत सम्मेलन के अध्यक्ष के रूप में निम्नलिखित में से किसे चुना गया था?",
            "a_hin":"मोतीलाल नेहरू",
            "b_hin":"महात्मा गांधी",
            "c_hin":"एम अली जिन्नाह",
            "d_hin":"शौकत अली",
            "e_hin":"उपरोक्त में से कोई नहीं/उपरोक्त में से एक से अधिक",
            "ans":"b"
        },       
        {
            "q_en":"Which of the following statements is incorrect regarding the Government of India Act 1919?",
            "a_en":"The Act made the Governor-General the chief executive authority.",
            "b_en":"The subjects were divided into two lists - reserved and transferred.",
            "c_en":"Direct election was introduced for the first time.",
            "d_en":"It introduced separate electoral for the Muslim community.",
            "e_en":"None of the above/More than one of the above",
            "q_hin":"भारत सरकार अधिनियम 1919 के संबंध में निम्नलिखित में से कौन सा कथन गलत है?",
            "a_hin":"इस अधिनियम ने गवर्नर-जनरल को मुख्य कार्यकारी प्राधिकारी बना दिया।",
            "b_hin":"विषयों को दो सूचियों में विभाजित किया गया था - आरक्षित और स्थानांतरित।",
            "c_hin":"पहली बार प्रत्यक्ष चुनाव की शुरुआत की गई थी।",
            "d_hin":"इसने मुस्लिम समुदाय के लिए अलग चुनाव की शुरुआत की।",
            "e_hin":"उपरोक्त में से कोई नहीं/उपरोक्त में से एक से अधिक",
            "ans":"d"
        },
        {
            "q_en":"On the banks of which of the following rivers did Pt. Jawaharlal Nehru unfurl the tricolour flag of Independence on the midnight of 31 December 1929?",
            "a_en":"Chenab",
            "b_en":"Jhelum",
            "c_en":"Ravi",
            "d_en":"Sutlej",
            "e_en":"None of the above/More than one of the above",
            "q_hin":"निम्नलिखित में से किस नदी के तट पर पंडित जवाहरलाल नेहरू ने 31 दिसंबर 1929 की आधी रात को स्वतंत्रता के ध्वज को फहराया?",
            "a_hin":"चिनाब",
            "b_hin":"झेलम",
            "c_hin":"रावी",
            "d_hin":"सतलज",
            "e_hin":"उपरोक्त में से कोई नहीं/उपरोक्त में से एक से अधिक",
            "ans":"c"
        },
        {
            "q_en":"When did the Gandhiji reached the coast of Dandi?",
            "a_en":"5 April, 1930",
            "b_en":"12 April, 1930",
            "c_en":"19 April, 1930",
            "d_en":"5 May, 1930",
            "e_en":"None of the above/More than one of the above",
            "q_hin":"गांधीजी दांडी तट पर कब पहुंचे?",
            "a_hin":"5 अप्रैल, 1930",
            "b_hin":"12 अप्रैल, 1930",
            "c_hin":"19 अप्रैल, 1930",
            "d_hin":"5 मई, 1930",
            "e_hin":"उपरोक्त में से कोई नहीं/उपरोक्त में से एक से अधिक",
            "ans":"a"
        },
        {
			"q_en":"Which among the following introduced the Provincial Autonomy in British India?",
            "a_en":"Cabinet Mission",
            "b_en":"Simon Commission",
            "c_en":"Government of India Act 1935",
            "d_en":"Government of India Act 1919",
            "e_en":"None of the above/More than one of the above",
            "q_hin":"निम्‍नलिखित में से किसने ब्रिटिश भारत में प्रांतीय स्‍वायत्तता शुरू की?",
            "a_hin":"कैबिनेट मिशन",
            "b_hin":"साइमन कमीशन",
            "c_hin":"भारत सरकार अधिनियम 1935",
            "d_hin":"भारत सरकार अधिनियम 1919",
            "e_hin":"उपरोक्त में से कोई नहीं/उपरोक्त में से एक से अधिक",
            "ans":"c"
		},       
		{
			"q_en":"Which of the following movement/reform/proposal was rejected by the Indian National Congress but was accepted by the Muslim League?",
            "a_en":"The Cripps Mission",
            "b_en":"August Offer",
            "c_en":"Morley - Minto Reforms",
            "d_en":"Home Rule Movement",
            "e_en":"None of the above/More than one of the above",
            "q_hin":"निम्नलिखित में से कौन-सा आंदोलन / सुधार / प्रस्ताव भारतीय राष्ट्रीय कांग्रेस द्वारा अस्वीकार कर दिया गया था लेकिन मुस्लिम संघ द्वारा स्वीकार किया गया था?",
            "a_hin":"क्रिप्स मिशन",
            "b_hin":"अगस्त ऑफर",
            "c_hin":"मॉर्ले - मिंटो सुधार",
            "d_hin":"होम रूल आंदोलन",
            "e_hin":"उपरोक्त में से कोई नहीं/उपरोक्त में से एक से अधिक",
            "ans":"b"
		},       
		{
			"q_en":"Who was the first person to observe 'Individual Satyagraha'?",
            "a_en":"Mahatma Gandhi",
            "b_en":"Govind Ballabh Pant",
            "c_en":"Sardar Vallabhbhai Patel",
            "d_en":"Vinoba Bhave",
            "e_en":"None of the above/More than one of the above",
            "q_hin":"First व्यक्तिगत सत्याग्रह ’का निरीक्षण करने वाला पहला व्यक्ति कौन था?",
            "a_hin":"महात्मा गांधी",
            "b_hin":"गोविंद बल्लभ पंत",
            "c_hin":"सरदार वल्लभभाई पटेल",
            "d_hin":"विनोबा भावे",
            "e_hin":"उपरोक्त में से कोई नहीं/उपरोक्त में से एक से अधिक",
            "ans":"d"
        },       
        {
            "q_en":"Rajaji formula was put forwarded in which among the following years?",
            "a_en":"1943",
            "b_en":"1942",
            "c_en":"1944",
            "d_en":"1945",
            "e_en":"None of the above/More than one of the above",
            "q_hin":"राजाजी फार्मूला को निम्नलिखित वर्षों में किसमें लाया गया था?",
            "a_hin":"1943",
            "b_hin":"1942",
            "c_hin":"1944",
            "d_hin":"1945",
            "e_hin":"उपरोक्त में से कोई नहीं/उपरोक्त में से एक से अधिक",
            "ans":"c"
        },       
        {
            "q_en":"Which among the following was not a cause of Bhil Movement?",
            "a_en":"Bhils became unemployed as native forces of Mewar were dissolved in 1818.",
            "b_en":"Col. James Tod tried to bring Bhils under his control.",
            "c_en":"Forest rights of Bhils were compromised.",
            "d_en":"Gametis increased their tax rates over Bhil villages",
            "e_en":"None of the above/More than one of the above",
            "q_hin":"निम्नलिखित में से कौनसा भील आंदोलन का कारण नहीं था?",
            "a_hin":"1818 में मेवाड़ की मूल सेनाओं को भंग करने के कारण भील बेरोजगार हो गए।",
            "b_hin":"कर्नल जेम्स टॉड ने भीलों को अपने नियंत्रण में लाने की कोशिश की।",
            "c_hin":"भीलों के वन अधिकारों से समझौता किया गया।",
            "d_hin":"गमेतीस ने भील गांवों पर अपनी कर दरों में वृद्धि की",
            "e_hin":"उपरोक्त में से कोई नहीं/उपरोक्त में से एक से अधिक",
            "ans":"d"
        },       
        {
            "q_en":"What is the main cause of the Indigo Rebellion in Bengal?",
            "a_en":"Forcefully collected rents and land taxes",
            "b_en":"British forced the farmers to grow indigo instead of food crops",
            "c_en":"Destroy the bonds, decrees, and other documents in the possession of the moneylenders",
            "d_en":"Forcefully banned the cultivation of indigo",
            "e_en":"None of the above/More than one of the above",
            "q_hin":"बंगाल में नील विद्रोह का मुख्य कारण क्या है?",
            "a_hin":"किराए और भू-कर को जबरन वसूलते थे",
            "b_hin":"ब्रिटिशों ने किसानों को खाद्य फसलों के बजाय नील उगाने के लिए मजबूर किया",
            "c_hin":"साहूकारों के कब्जे में बंधों, फरमानों और अन्य दस्तावेजों को नष्ट किया जाता था",
            "d_hin":"नील की खेती पर प्रतिबंध लगा दिया गया था",
            "e_hin":"उपरोक्त में से कोई नहीं/उपरोक्त में से एक से अधिक",
            "ans":"b"
        },       
        {
            "q_en":"Which among the following Indian newspapers had to stop its publication because of Licensing Regulations Act, 1823?",
            "a_en":"Bengal Gazette",
            "b_en":"Amrita Bazar Patrika",
            "c_en":"Mirat-ul-Akhbar",
            "d_en":"Bharat Mihir",
            "e_en":"None of the above/More than one of the above",
            "q_hin":"निम्नलिखित में से किस भारतीय समाचार पत्र को लाइसेंसिंग विनियम अधिनियम, 1823 के कारण अपना प्रकाशन बंद करना पड़ा?",
            "a_hin":"बंगाल गजट",
            "b_hin":"अमृता बाजार पत्रिका",
            "c_hin":"मिरात-उल-अखबार",
            "d_hin":"भरत मिहिर",
            "e_hin":"उपरोक्त में से कोई नहीं/उपरोक्त में से एक से अधिक",
            "ans":"c"
        },       
        {
            "q_en":"Who had presided over the inaugural session of the 'All India Trade Union Congress' held in 1920?",
            "a_en":"Lala Lajpat Rai",
            "b_en":"Bal Gangadhar Tilak",
            "c_en":"Bipin Chandra Pal",
            "d_en":"Surendra Nath Banerjee",
            "e_en":"None of the above/More than one of the above",
            "q_hin":"1920 में आयोजित 'अखिल भारतीय मजदूर संघ काँग्रेस' के उद्घाटन सत्र की अध्यक्षता किसने की थी?",
            "a_hin":"लाला लाजपत राय",
            "b_hin":"बाल गंगाधर तिलक",
            "c_hin":"बिपिन चंद्र पाल",
            "d_hin":"सुरेंद्र नाथ बनर्जी",
            "e_hin":"उपरोक्त में से कोई नहीं/उपरोक्त में से एक से अधिक",
            "ans":"a"
        },
        {
            "q_en":"In which year was the Hunter Commission appointed by Lord Ripon for education reforms?",
            "a_en":"1879",
            "b_en":"1867",
            "c_en":"1857",
            "d_en":"1882",
            "e_en":"None of the above/More than one of the above",
            "q_hin":"लॉर्ड रिपन द्वारा शिक्षा सुधार के लिए हंटर आयोग की नियुक्ति किस वर्ष की गई थी?",
            "a_hin":"1879",
            "b_hin":"1867",
            "c_hin":"1857",
            "d_hin":"1882",
            "e_hin":"उपरोक्त में से कोई नहीं/उपरोक्त में से एक से अधिक",
            "ans":"d"
        },
        {
            "q_en":"Who had merged Sikkim in British India?",
            "a_en":"Lord Hastings",
            "b_en":"Lord William Bentinck",
            "c_en":"Lord Dalhousie",
            "d_en":"Lord Auckland",
            "e_en":"None of the above/More than one of the above",
            "q_hin":"सिक्किम का ब्रिटिश भारत में विलय किसने किया था?",
            "a_hin":"लॉर्ड हेस्टिंग्स",
            "b_hin":"लॉर्ड विलियम बेंटिक",
            "c_hin":"लॉर्ड डलहौजी",
            "d_hin":"लॉर्ड ऑकलैंड",
            "e_hin":"उपरोक्त में से कोई नहीं/उपरोक्त में से एक से अधिक",
            "ans":"c"
        },
        {
			"q_en":"In which of the following sessions of Indian National Congress, the resolution of Swadeshi was adopted?",
            "a_en":"Madras Session 1903",
            "b_en":"Bombay Session 1904",
            "c_en":"Banaras Session 1905",
            "d_en":"Calcutta Session 1906",
            "e_en":"None of the above/More than one of the above",
            "q_hin":"भारतीय राष्ट्रीय कांग्रेस के निम्नलिखित में से किस अधिवेशन में स्वदेशी के प्रस्ताव को स्वीकार किया गया था?",
            "a_hin":"मद्रास अधिवेशन 1903",
            "b_hin":"बॉम्बे अधिवेशन 1904",
            "c_hin":"बनारस अधिवेशन 1905",
            "d_hin":"कलकत्ता अधिवेशन 1906",
            "e_hin":"उपरोक्त में से कोई नहीं/उपरोक्त में से एक से अधिक",
            "ans":"d"
		},       
		{
			"q_en":"Who among the following was elected as the President of the Indian National Congress in the years 1938 and 1939?",
            "a_en":"Annie Besant",
            "b_en":"C Rajagopalachari",
            "c_en":"Rajendra Prasad",
            "d_en":"Subhash Chandra Bose",
            "e_en":"None of the above/More than one of the above",
            "q_hin":"निम्नलिखित में से किसे 1938 और 1939 में भारतीय राष्ट्रीय कांग्रेस के अध्यक्ष के रूप में चुना गया था?",
            "a_hin":"एनी बेसेंट",
            "b_hin":"सी राजगोपालाचारी",
            "c_hin":"राजेन्द्र प्रसाद",
            "d_hin":"सुभाष चंद्र बोस",
            "e_hin":"उपरोक्त में से कोई नहीं/उपरोक्त में से एक से अधिक",
            "ans":"d"
		},       
		{
			"q_en":"The book 'India Wins Freedom' was written by :",
            "a_en":"Jawaharlal Nehru",
            "b_en":"Mahatma Gandhi",
            "c_en":"Vallabhbhai Patel",
            "d_en":"Abul Kalam Azad",
            "e_en":"None of the above/More than one of the above",
            "q_hin":"पुस्तक 'इंडिया विन्स फ्रीडम' किसके द्वारा लिखी गई थी :",
            "a_hin":"जवाहर लाल नेहरू",
            "b_hin":"महात्मा गांधी",
            "c_hin":"वल्लभभाई पटेल",
            "d_hin":"अबुल कलाम आज़ाद",
            "e_hin":"उपरोक्त में से कोई नहीं/उपरोक्त में से एक से अधिक",
            "ans":"d"
        },       
        {
            "q_en":"'We must make our political democracy a social democracy as well'. Who had said this line?",
            "a_en":"Maulana Abul Kalam Azad",
            "b_en":"Pandit Jawaharlal Nehru",
            "c_en":"B.R. Ambedkar",
            "d_en":"Dr. Rajendra Prasad",
            "e_en":"None of the above/More than one of the above",
            "q_hin":"'हमें अपने राजनीतिक लोकतंत्र को एक सामाजिक लोकतंत्र भी बनाना चाहिए।' किसने कहा था ये लाइन?",
            "a_hin":"मौलाना अबुल कलाम आज़ाद",
            "b_hin":"पंडित जवाहरलाल नेहरू",
            "c_hin":"बी आर अंबेडकर",
            "d_hin":"डॉ राजेंद्र प्रसाद",
            "e_hin":"उपरोक्त में से कोई नहीं/उपरोक्त में से एक से अधिक",
            "ans":"c"
        },       
        {
            "q_en":"Which among the following opinion about INC has been given by Bipin Chandra Pal?",
            "a_en":"INC represents only a microscopic minorities",
            "b_en":"INC playing with bubbles",
            "c_en":"INC is a begging institute",
            "d_en":"INC should be distinguished between begging and claiming the rights",
            "e_en":"None of the above/More than one of the above",
            "q_hin":"कांग्रेस के बारे में निम्नलिखित में से कौन बिपिन चंद्र पाल द्वारा दिया गया है?",
            "a_hin":"कांग्रेस केवल एक सूक्ष्म अल्पसंख्यक का प्रतिनिधित्व करता है",
            "b_hin":"कांग्रेस बुलबुले के साथ खेल रहा है",
            "c_hin":"कांग्रेस एक भीख मांगने वाला संस्थान है",
            "d_hin":"कांग्रेस को भीख मांगने और अधिकारों का दावा करने के बीच अंतर करना चाहिए",
            "e_hin":"उपरोक्त में से कोई नहीं/उपरोक्त में से एक से अधिक",
            "ans":"b"
        }
	]
}