{
    "QuizQuestions": [
        {
            "q_en": "Which one of the following states of India has the lowest female child sex ratio 0-6 years?",
            "a_en": "Gujarat",
            "b_en": "Punjab",
            "c_en": "Haryana",
            "d_en": "Himachal Pradesh",
            "q_hin": "भारत के निम्नलिखित राज्यों में से किस राज्य में महिला बाल लिंगानुपात 0-6 वर्ष सबसे कम है?",
            "a_hin": "गुजरात",
            "b_hin": "पंजाब",
            "c_hin": "हरियाणा",
            "d_hin": "हिमाचल प्रदेश",
            "ans": "c"
        },
        {
            "q_en": "Which one of the following Union Territories of India has the highest literacy rate?",
            "a_en": "Lakshadweep",
            "b_en": "Daman and Diu",
            "c_en": "Chandigarh",
            "d_en": "Andaman and Nicobar Islands",
            "q_hin": "निम्नलिखित में से भारत के किस केंद्र शासित प्रदेश में साक्षरता दर सबसे अधिक है?",
            "a_hin": "लक्षद्वीप",
            "b_hin": "दमन और दीव",
            "c_hin": "चंडीगढ़",
            "d_hin": "अंडमान और निकोबार द्वीप समूह",
            "ans": "a"
        },
        {
            "q_en": "Which one of the following towns is not located on a river bank?",
            "a_en": "Agra",
            "b_en": "Patna",
            "c_en": "Bhopal",
            "d_en": "Kolkata",
            "q_hin": "निम्नलिखित नगरों में से कौन-सा एक नदी तट पर स्थित नहीं है?",
            "a_hin": "आगरा",
            "b_hin": "पटना",
            "c_hin": "भोपाल",
            "d_hin": "कोलकाता",
            "ans": "c"
        },
        {
            "q_en": "Which one of the following is not the part of the definition of a town as per the census of India?",
            "a_en": "Population density of 400 persons per sq km",
            "b_en": "Presence of municipality, corporation, etc.",
            "c_en": "More than 75% of the population engaged in primary sector",
            "d_en": "Population size of more than 5,000 persons.",
            "q_hin": "निम्नलिखित में से कौन भारत की जनगणना के अनुसार एक शहर की परिभाषा का हिस्सा नहीं है?",
            "a_hin": "जनसंख्या घनत्व 400 व्यक्ति प्रति वर्ग किमी",
            "b_hin": "नगर पालिका, निगम, आदि की उपस्थिति।",
            "c_hin": "75 प्रतिशत से अधिक जनसंख्या प्राथमिक क्षेत्र में लगी हुई है",
            "d_hin": "5,000 से अधिक व्यक्तियों की जनसंख्या का आकार।",
            "ans": "c"
        },
        {
            "q_en": "In which one of the following environments does one expect the presence of dispersed rural settlements?",
            "a_en": "Alluvial plains of Ganga",
            "b_en": "Arid and semi-arid regions of Rajasthan",
            "c_en": "Lower valleys of Himalayas",
            "d_en": "Forests and hills in north-east",
            "q_hin": "निम्नलिखित में से किस पर्यावरण में परिक्षिप्त हुई ग्रामीण बस्तियों की उपस्थिति की अपेक्षा की जाती है?",
            "a_hin": "गंगा के जलोढ़ मैदान",
            "b_hin": "राजस्थान के शुष्क और अर्ध-शुष्क प्रदेश",
            "c_hin": "हिमालय की निचली घाटियाँ",
            "d_hin": "उत्तर-पूर्व में वन और पहाड़ियाँ",
            "ans": "d"
        },
        {
            "q_en": "Which one of the following groups of cities has been arranged in the sequence of their ranks i.e. 1, 2, 3 and 4 in decreasing order of their size according to the population?",
            "a_en": "Greater Mumbai, Bengaluru, Kolkata, Chennai",
            "b_en": "Delhi, Greater Mumbai, Chennai, Kolkata",
            "c_en": "Kolkata, Greater Mumbai, Chennai, Delhi",
            "d_en": "Greater Mumbai, Kolkata, Delhi, Chennai",
            "q_hin": "शहरों के निम्नलिखित समूहों में से किस एक को जनसंख्या के अनुसार उनके आकार के घटते क्रम अर्थात 1, 2, 3 और 4 के क्रम में व्यवस्थित किया गया है?",
            "a_hin": "बृहन्मुंबई, बेंगलुरु, कोलकाता, चेन्नई",
            "b_hin": "दिल्ली, बृहन्मुंबई, चेन्नई, कोलकाता",
            "c_hin": "कोलकाता, बृहन्मुंबई, चेन्नई, दिल्ली",
            "d_hin": "बृहन्मुंबई, कोलकाता, दिल्ली, चेन्नई",
            "ans": "d"
        },
        {
            "q_en": "Which one of the following is not a land-use category?",
            "a_en": "Fallow land",
            "b_en": "Net Area Sown",
            "c_en": "Marginal land",
            "d_en": "Culturable Wasteland",
            "q_hin": "निम्नलिखित में से कौन-सी एक भूमि-उपयोग श्रेणी नहीं है?",
            "a_hin": "परती भूमि",
            "b_hin": "शुद्ध बोया गया क्षेत्र",
            "c_hin": "सीमांत भूमि",
            "d_hin": "कृषि योग्य बंजर भूमि",
            "ans": "c"
        },
        {
            "q_en": "Which one of the following is the main reason due to which share of the forest has shown an increase in the last forty years?",
            "a_en": "Extensive and efficient efforts of afforestation",
            "b_en": "Increase in community forest land",
            "c_en": "Increase in notified area allocated for forest growth",
            "d_en": "Better peoples’ participation in managing forest area.",
            "q_hin": "निम्नलिखित में से कौन-सा मुख्य कारण है जिसके कारण पिछले चालीस वर्षों में वनों के हिस्से में वृद्धि हुई है?",
            "a_hin": "वनीकरण के व्यापक और कुशल प्रयास",
            "b_hin": "सामुदायिक वन भूमि में वृद्धि",
            "c_hin": "वन विकास के लिए आवंटित अधिसूचित क्षेत्र में वृद्धि",
            "d_hin": "वन क्षेत्र के प्रबंधन में लोगों की बेहतर भागीदारी।",
            "ans": "c"
        },
        {
            "q_en": "Which one of the following is the main form of degradation in irrigated areas?",
            "a_en": "Gully erosion",
            "b_en": "Salinisatin of soils",
            "c_en": "Wind erosion",
            "d_en": "Siltation of land",
            "q_hin": "निम्नलिखित में से कौन सिंचित क्षेत्रों में निम्नीकरण का मुख्य रूप है?",
            "a_hin": "अवनालिका अपक्षरण",
            "b_hin": "मृदा का लवणीकरण",
            "c_hin": "पवन कटाव",
            "d_hin": "भूमि की गाद",
            "ans": "b"
        },
        {
            "q_en": "Which one of the following crops is not cultivated under dryland farming?",
            "a_en": "Ragi",
            "b_en": "Groundnut",
            "c_en": "Jowar",
            "d_en": "Sugarcane",
            "q_hin": "निम्नलिखित में से किस फसल की खेती शुष्क भूमि में नहीं की जाती है?",
            "a_hin": "रागी",
            "b_hin": "मूंगफली",
            "c_hin": "ज्वार",
            "d_hin": "गन्ना",
            "ans": "d"
        }
    ]
}